tavoai/__init__.py
tavoai/py.typed
tavoai/sdk/__init__.py
tavoai/sdk/client.py
tavoai/sdk/decorators.py
tavoai/sdk/exceptions.py
tavoai/sdk/models.py
tavoai/sdk/utils.py
tavoai_sdk-0.1.0.dist-info/licenses/LICENSE
tavoai_sdk-0.1.0.dist-info/METADATA
tavoai_sdk-0.1.0.dist-info/WHEEL
tavoai_sdk-0.1.0.dist-info/top_level.txt
tavoai_sdk-0.1.0.dist-info/RECORD
