Metadata-Version: 2.4
Name: tavoai-sdk
Version: 0.1.0
Summary: TavoAI SDK for AI risk controls evaluation
Home-page: https://github.com/TavoAI/tavo-python-sdk
Author: TavoAI
Author-email: TavoAI <info@tavoai.com>
License: MIT
Project-URL: Homepage, https://github.com/TavoAI/tavo-python-sdk
Project-URL: Documentation, https://github.com/TavoAI/tavo-python-sdk#readme
Project-URL: Bug Tracker, https://github.com/TavoAI/tavo-python-sdk/issues
Project-URL: Source, https://github.com/TavoAI/tavo-python-sdk
Keywords: ai,guardrails,regulation,controls,compliance
Classifier: Development Status :: 3 - Alpha
Classifier: Intended Audience :: Developers
Classifier: License :: OSI Approved :: MIT License
Classifier: Programming Language :: Python :: 3
Classifier: Programming Language :: Python :: 3.8
Classifier: Programming Language :: Python :: 3.9
Classifier: Programming Language :: Python :: 3.10
Classifier: Programming Language :: Python :: 3.11
Classifier: Topic :: Software Development :: Libraries
Requires-Python: >=3.8
License-File: LICENSE
Requires-Dist: requests>=2.25.0
Requires-Dist: colorlog>=6.7.0
Provides-Extra: dev
Requires-Dist: pytest>=6.0.0; extra == "dev"
Requires-Dist: pytest-cov>=2.12.0; extra == "dev"
Requires-Dist: black>=21.5b2; extra == "dev"
Requires-Dist: isort>=5.9.1; extra == "dev"
Requires-Dist: mypy>=0.812; extra == "dev"
Requires-Dist: flake8>=3.9.2; extra == "dev"
Dynamic: license-file
